azure/mgmt/automanage/__init__.py
azure/mgmt/automanage/_automanage_client.py
azure/mgmt/automanage/_configuration.py
azure/mgmt/automanage/_patch.py
azure/mgmt/automanage/_vendor.py
azure/mgmt/automanage/_version.py
azure/mgmt/automanage/py.typed
azure/mgmt/automanage/aio/__init__.py
azure/mgmt/automanage/aio/_automanage_client.py
azure/mgmt/automanage/aio/_configuration.py
azure/mgmt/automanage/aio/_patch.py
azure/mgmt/automanage/aio/operations/__init__.py
azure/mgmt/automanage/aio/operations/_best_practices_operations.py
azure/mgmt/automanage/aio/operations/_best_practices_versions_operations.py
azure/mgmt/automanage/aio/operations/_configuration_profile_assignments_operations.py
azure/mgmt/automanage/aio/operations/_configuration_profile_hci_assignments_operations.py
azure/mgmt/automanage/aio/operations/_configuration_profile_hcrp_assignments_operations.py
azure/mgmt/automanage/aio/operations/_configuration_profiles_operations.py
azure/mgmt/automanage/aio/operations/_configuration_profiles_versions_operations.py
azure/mgmt/automanage/aio/operations/_hci_reports_operations.py
azure/mgmt/automanage/aio/operations/_hcrp_reports_operations.py
azure/mgmt/automanage/aio/operations/_operations.py
azure/mgmt/automanage/aio/operations/_patch.py
azure/mgmt/automanage/aio/operations/_reports_operations.py
azure/mgmt/automanage/aio/operations/_service_principals_operations.py
azure/mgmt/automanage/models/__init__.py
azure/mgmt/automanage/models/_automanage_client_enums.py
azure/mgmt/automanage/models/_models_py3.py
azure/mgmt/automanage/models/_patch.py
azure/mgmt/automanage/operations/__init__.py
azure/mgmt/automanage/operations/_best_practices_operations.py
azure/mgmt/automanage/operations/_best_practices_versions_operations.py
azure/mgmt/automanage/operations/_configuration_profile_assignments_operations.py
azure/mgmt/automanage/operations/_configuration_profile_hci_assignments_operations.py
azure_mgmt_automanage-1.0.0.dist-info/LICENSE
azure_mgmt_automanage-1.0.0.dist-info/METADATA
azure_mgmt_automanage-1.0.0.dist-info/WHEEL
azure_mgmt_automanage-1.0.0.dist-info/top_level.txt
azure_mgmt_automanage-1.0.0.dist-info/RECORD
